Workbook

Sheet Products
A1: Product Code | B1: Product Name | C1: Category | D1: Description | E1: Cost Price | F1: Market Price | G1: Selling Price | H1: Profit | I1: Stock Qty | J1: Delivery Fee | K1: COD Available | L1: Photo 1 | M1: Photo 2 | N1: Photo 3 | O1: photo 4 | P1: photo 5 | Q1: Video Link | R1: Facebook Post Link | S1: Supplier | T1: Date Added | U1: Status
A3: P00093 | B3: A9 Mini Wireless Camera | C3: Electronics | E3: 1000 | F3: 1950 | G3: 1450 | H3: =G3-E3 -> 450 | J3: 450 | K3: TRUE | L3: Products_Images/P00093A9 Mini Wireless Camera.Photo 1.113408.jpg | S3: A2Z | T3: 46196 | U3: =IF(I3<=0,"Out of Stock","In Stock") -> Out of Stock
A4: P08391 | B4: S2 Mini WiFi Camera | C4: Electronics | E4: 2050 | F4: 2850 | G4: 2390 | H4: =G4-E4 -> 340 | K4: TRUE | L4: Products_Images/P08391S2 Mini WiFi Camera.Photo 1.170857.png | M4: Products_Images/P08391S2 Mini WiFi Camera.Photo 2.170857.jpg | N4: Products_Images/P08391S2 Mini WiFi Camera.Photo 3.170857.jpg | O4: Products_Images/P08391S2 Mini WiFi Camera.photo 4.170901.jpg | P4: Products_Images/P08391S2 Mini WiFi Camera.photo 5.170901.jpg | T4: 46196 | U4: =IF(I4<=0,"Out of Stock","In Stock") -> Out of Stock
A5: P05995 | B5: Pix-Link WiFi Smart Camera | C5: Electronics | E5: 1900 | F5: 2650 | G5: 2290 | H5: =G5-E5 -> 390 | K5: TRUE | L5: Products_Images/P05995Pix-Link WiFi Smart Camera.Photo 1.044429.jpg | M5: Products_Images/P05995Pix-Link WiFi Smart Camera.Photo 2.044429.jpg | N5: Products_Images/P05995Pix-Link WiFi Smart Camera.Photo 3.044429.jpg | O5: Products_Images/P05995Pix-Link WiFi Smart Camera.photo 4.044438.jpg | T5: 46196 | U5: =IF(I5<=0,"Out of Stock","In Stock") -> Out of Stock
A6: P01832 | B6: K9 Wireless Microphone | C6: Electronics | E6: 1100 | F6: 1590 | G6: 1390 | H6: =G6-E6 -> 290 | K6: TRUE | L6: Products_Images/P01832K9 Wireless Microphone.Photo 1.033246.jpg | T6: 46196 | U6: =IF(I6<=0,"Out of Stock","In Stock") -> Out of Stock
A7: P06779 | B7: K35 Dual Wireless Microphone | C7: Electronics | E7: 1200 | F7: 1650 | G7: 1550 | H7: =G7-E7 -> 350 | K7: TRUE | L7: Products_Images/P06779K35 Dual Wireless Microphone.Photo 1.055224.jpg | M7: Products_Images/P06779K35 Dual Wireless Microphone.Photo 2.055224.jpg | N7: Products_Images/P06779K35 Dual Wireless Microphone.Photo 3.055224.jpg | O7: Products_Images/P06779K35 Dual Wireless Microphone.photo 4.055227.jpg | T7: 46196 | U7: =IF(I7<=0,"Out of Stock","In Stock") -> Out of Stock
A8: P08660 | B8: REMAI PRO88 Wireless Earbud | C8: Electronics | E8: 975 | F8: 1750 | G8: 1560 | H8: =G8-E8 -> 585 | K8: TRUE | L8: Products_Images/P08660REMAI PRO88 Wireless Earbud.Photo 1.174004.png | T8: 46196 | U8: =IF(I8<=0,"Out of Stock","In Stock") -> Out of Stock
A9: P04115 | B9: Y47 Cat Headset | C9: Electronics | E9: 1100 | F9: 1550 | G9: 1390 | H9: =G9-E9 -> 290 | K9: TRUE | L9: Products_Images/P04115Y47 Cat Headset.Photo 1.171757.jpg | T9: 46196 | U9: =IF(I9<=0,"Out of Stock","In Stock") -> Out of Stock
A10: P01469 | B10: T800 Ultra Smart Watch | C10: Electronics | E10: 1300 | F10: 2250 | G10: 1750 | H10: =G10-E10 -> 450 | K10: TRUE | L10: Products_Images/P01469T800 Ultra Smart Watch.Photo 1.133611.jpg | T10: 46196 | U10: =IF(I10<=0,"Out of Stock","In Stock") -> Out of Stock
A11: P00260 | B11: Projection Lamp (Star Light) | C11: Electronics | E11: 850 | F11: 1250 | G11: 1050 | H11: =G11-E11 -> 200 | K11: TRUE | L11: Products_Images/P00260Projection Lamp (Star Light).Photo 1.085224.jpg | M11: Products_Images/P00260Projection Lamp (Star Light).Photo 2.085223.jpg | N11: Products_Images/P00260Projection Lamp (Star Light).Photo 3.085223.jpg | O11: Products_Images/P00260Projection Lamp (Star Light).photo 4.085227.jpg | P11: Products_Images/P00260Projection Lamp (Star Light).photo 5.085228.jpg | T11: 46196 | U11: =IF(I11<=0,"Out of Stock","In Stock") -> Out of Stock
A12: P03400 | B12: Bluetooth Electronic Weight Scale | C12: Electronics | E12: 1200 | F12: 1950 | G12: 1550 | H12: =G12-E12 -> 350 | L12: Products_Images/P03400Bluetooth Electronic Weight Scale.Photo 1.085805.jpg | M12: Products_Images/P03400Bluetooth Electronic Weight Scale.Photo 2.085805.jpg | N12: Products_Images/P03400Bluetooth Electronic Weight Scale.Photo 3.085805.jpg | T12: 46196 | U12: =IF(I12<=0,"Out of Stock","In Stock") -> Out of Stock
A13: P04252 | B13: Smart Wireless Doorbell | C13: Electronics | E13: 900 | H13: =G13-E13 -> -900 | T13: 46196 | U13: =IF(I13<=0,"Out of Stock","In Stock") -> Out of Stock
A14: P02543 | B14: Inflatable Air Sofa With Foot Rest | C14: Home & Living | E14: 3550 | F14: 4360 | H14: =G14-E14 -> -3550 | L14: Products_Images/P02543Inflatable Air Sofa With Foot Rest.Photo 1.174343.jpg | T14: 46196 | U14: =IF(I14<=0,"Out of Stock","In Stock") -> Out of Stock
A15: P05197 | B15: Inflatable Car Air Mattress | C15: Car Accessories | E15: 3700 | F15: 4600 | H15: =G15-E15 -> -3700 | L15: Products_Images/P05197Inflatable Car Air Mattress.Photo 1.174803.jpg | T15: 46196 | U15: =IF(I15<=0,"Out of Stock","In Stock") -> Out of Stock
A16: P07633 | B16: Jewelry Cleaning Machine | C16: Jewelry & Accessories | E16: 850 | F16: 1000 | H16: =G16-E16 -> -850 | L16: Products_Images/P07633Jewelry Cleaning Machine.Photo 1.175115.jpg | T16: 46196 | U16: =IF(I16<=0,"Out of Stock","In Stock") -> Out of Stock
A17: P03951 | B17: K-12 Colorful Karaoke Sound System | C17: Electronics | E17: 1150 | F17: 1600 | G17: 1350 | H17: =G17-E17 -> 200 | L17: Products_Images/P03951K-12 Colorful Karaoke Sound System.Photo 1.090637.jpg | M17: Products_Images/P03951K-12 Colorful Karaoke Sound System.Photo 2.090637.jpg | N17: Products_Images/P03951K-12 Colorful Karaoke Sound System.Photo 3.090637.jpg | O17: Products_Images/P03951K-12 Colorful Karaoke Sound System.photo 4.090639.jpg | T17: 46196 | U17: =IF(I17<=0,"Out of Stock","In Stock") -> Out of Stock
A18: P06077 | B18: KH-740 Fascial Gun Massager | C18: Fitness & Health | E18: 2300 | F18: 2900 | H18: =G18-E18 -> -2300 | L18: Products_Images/P06077KH-740 Fascial Gun Massager.Photo 1.175504.jpg | T18: 46196 | U18: =IF(I18<=0,"Out of Stock","In Stock") -> Out of Stock
A19: P08035 | B19: Modern Square Soap Dispenser | C19: Home & Living | E19: 525 | F19: 650 | H19: =G19-E19 -> -525 | L19: Products_Images/P08035Modern Square Soap Dispenser.Photo 1.175712.jpg | T19: 46196 | U19: =IF(I19<=0,"Out of Stock","In Stock") -> Out of Stock
A20: P01934 | B20: Diamond Crystal Moon Shaped Rechargeable Table Lamp | C20: Home & Living | E20: 1300 | F20: 1900 | H20: =G20-E20 -> -1300 | L20: Products_Images/P01934Diamond Crystal Moon Shaped R_1979645513851130205.Photo 1.175901.jpg | T20: 46196 | U20: =IF(I20<=0,"Out of Stock","In Stock") -> Out of Stock
A21: P00106 | B21: Nima Electric Grinder | C21: Kitchen & Dining | E21: 1300 | F21: 1900 | H21: =G21-E21 -> -1300 | L21: Products_Images/P00106Nima Electric Grinder.Photo 1.180052.jpg | T21: 46196 | U21: =IF(I21<=0,"Out of Stock","In Stock") -> Out of Stock
A22: P01933 | B22: Diamond Crystal Rechargeable Table Lamp | C22: Home & Living | E22: 1300 | F22: 1900 | H22: =G22-E22 -> -1300 | L22: Products_Images/P01933Diamond Crystal Rechargeable Table Lamp.Photo 1.180224.jpg | T22: 46196 | U22: =IF(I22<=0,"Out of Stock","In Stock") -> Out of Stock
A23: P04822 | B23: Diamond Crystal Oval Shaped Rechargeable Table Lamp | C23: Home & Living | E23: 1300 | F23: 1900 | H23: =G23-E23 -> -1300 | L23: Products_Images/P04822Diamond Crystal Oval Shaped R_3741592320910708969.Photo 1.180438.jpg | T23: 46196 | U23: =IF(I23<=0,"Out of Stock","In Stock") -> Out of Stock
A24: P07362 | B24: Pen Laser Pointer | C24: Electronics | E24: 900 | F24: 1600 | G24: 1290 | H24: =G24-E24 -> 390 | L24: Products_Images/P07362Pen Laser Pointer.Photo 1.180559.jpg | T24: 46196 | U24: =IF(I24<=0,"Out of Stock","In Stock") -> Out of Stock
A25: P05944 | B25: Plush Breathing Teddy Bear | C25: Toys & Kids | E25: 1300 | F25: 1700 | G25: 1590 | H25: =G25-E25 -> 290 | L25: Products_Images/P05944Plush Breathing Teddy Bear.Photo 1.180724.jpg | M25: Products_Images/P05944Plush Breathing Teddy Bear.Photo 2.114034.jpg | N25: Products_Images/P05944Plush Breathing Teddy Bear.Photo 3.114034.jpg | O25: Products_Images/P05944Plush Breathing Teddy Bear.photo 4.114034.jpg | T25: 46196 | U25: =IF(I25<=0,"Out of Stock","In Stock") -> Out of Stock
A26: P05676 | B26: Portable Mini Foot Air Pump With Meter | C26: Car Accessories | E26: 1100 | F26: 1550 | H26: =G26-E26 -> -1100 | L26: Products_Images/P05676Portable Mini Foot Air Pump With Meter.Photo 1.180917.jpg | T26: 46196 | U26: =IF(I26<=0,"Out of Stock","In Stock") -> Out of Stock
A27: P04698 | B27: Push Up Board | C27: Fitness & Health | E27: 1650 | F27: 2460 | H27: =G27-E27 -> -1650 | L27: Products_Images/P04698Push Up Board.Photo 1.181409.jpg | T27: 46196 | U27: =IF(I27<=0,"Out of Stock","In Stock") -> Out of Stock
A28: P06002 | B28: Selfie Stick With Fill Light & Remote | C28: Electronics | E28: 650 | F28: 1850 | G28: 1350 | H28: =G28-E28 -> 700 | L28: Products_Images/P06002Selfie Stick With Fill Light & Remote.Photo 1.181927.jpg | T28: 46196 | U28: =IF(I28<=0,"Out of Stock","In Stock") -> Out of Stock
A29: P03596 | B29: Single Bed Foldable Mosquito Net - (L - 5ft , W - 6ft) | C29: Home & Living | E29: 1900 | F29: 2690 | H29: =G29-E29 -> -1900 | L29: Products_Images/P03596Single Bed Foldable Mosquito _6842759353846676944.Photo 1.182351.jpg | T29: 46196 | U29: =IF(I29<=0,"Out of Stock","In Stock") -> Out of Stock
A30: P02671 | B30: Slim & Lift Vest | C30: Fitness & Health | E30: 850 | F30: 1600 | H30: =G30-E30 -> -850 | L30: Products_Images/P02671Slim & Lift Vest.Photo 1.182547.jpg | T30: 46196 | U30: =IF(I30<=0,"Out of Stock","In Stock") -> Out of Stock
A31: P00009 | B31: Solar Sensor Light | C31: Home & Living | E31: 1090 | F31: 1560 | H31: =G31-E31 -> -1090 | L31: Products_Images/P00009Solar Sensor Light.Photo 1.182811.jpg | T31: 46196 | U31: =IF(I31<=0,"Out of Stock","In Stock") -> Out of Stock
A32: P00004 | B32: Solar Street Lamp | C32: Home & Living | E32: 1500 | F32: 2600 | H32: =G32-E32 -> -1500 | L32: Products_Images/P00004Solar Street Lamp.Photo 1.183416.jpg | T32: 46196 | U32: =IF(I32<=0,"Out of Stock","In Stock") -> Out of Stock
A33: P08037 | B33: Stationery Holder - MP | C33: Home & Living | E33: 525 | F33: 1300 | H33: =G33-E33 -> -525 | L33: Products_Images/P08037Stationery Holder - MP.Photo 1.183159.jpg | T33: 46197 | U33: =IF(I33<=0,"Out of Stock","In Stock") -> Out of Stock
A34: P06931 | B34: Stitch Plush Breathing Teddy | C34: Toys & Kids | E34: 1700 | F34: 2500 | H34: =G34-E34 -> -1700 | L34: Products_Images/P06931Stitch Plush Breathing Teddy.Photo 1.183358.jpg | T34: 46197 | U34: =IF(I34<=0,"Out of Stock","In Stock") -> Out of Stock
A35: P08209 | B35: Swan Shaped Crystal LED Lamp | C35: Home & Living | E35: 1300 | F35: 1900 | H35: =G35-E35 -> -1300 | L35: Products_Images/P08209Swan Shaped Crystal LED Lamp.Photo 1.183623.jpg | T35: 46197 | U35: =IF(I35<=0,"Out of Stock","In Stock") -> Out of Stock
A36: P07022 | B36: Transparent Hair Clipper - YX-999 | C36: Beauty & Personal Care | E36: 1000 | F36: 1550 | H36: =G36-E36 -> -1000 | L36: Products_Images/P07022Transparent Hair Clipper - YX-999.Photo 1.183915.jpg | T36: 46197 | U36: =IF(I36<=0,"Out of Stock","In Stock") -> Out of Stock
A37: P04532 | B37: Ultrasonic Aroma Humidifier | C37: Home & Living | E37: 975 | F37: 1690 | G37: 1290 | H37: =G37-E37 -> 315 | L37: Products_Images/P04532Ultrasonic Aroma Humidifier.Photo 1.184041.jpg | T37: 46197 | U37: =IF(I37<=0,"Out of Stock","In Stock") -> Out of Stock
A38: P00151 | B38: USB Juicer | C38: Kitchen & Dining | E38: 900 | F38: 1690 | G38: 1290 | H38: =G38-E38 -> 390 | L38: Products_Images/P00151USB Juicer.Photo 1.184155.jpg | M38: Products_Images/P00151USB Juicer.Photo 2.052423.jpg | N38: Products_Images/P00151USB Juicer.Photo 3.052423.jpg | O38: Products_Images/P00151USB Juicer.photo 4.052423.jpg | T38: 46197 | U38: =IF(I38<=0,"Out of Stock","In Stock") -> Out of Stock
A39: P00679 | B39: Vaccum Flask Set | C39: Kitchen & Dining | E39: 1100 | F39: 1650 | H39: =G39-E39 -> -1100 | L39: Products_Images/P00679Vaccum Flask Set.Photo 1.184336.jpg | T39: 46197 | U39: =IF(I39<=0,"Out of Stock","In Stock") -> Out of Stock
A40: P02549 | B40: Electric Mini Waffle Maker | C40: Kitchen & Dining | E40: 1600 | F40: 2350 | H40: =G40-E40 -> -1600 | L40: Products_Images/P02549Electric Mini Waffle Maker.Photo 1.184522.jpg | T40: 46197 | U40: =IF(I40<=0,"Out of Stock","In Stock") -> Out of Stock
A41: P02528 | B41: Washing Machine Cover | C41: Home & Living | E41: 500 | F41: 1300 | H41: =G41-E41 -> -500 | L41: Products_Images/P02528Washing Machine Cover.Photo 1.184710.jpg | T41: 46197 | U41: =IF(I41<=0,"Out of Stock","In Stock") -> Out of Stock
A42: P06267 | B42: WaterProof Motor Bike Cover - 100x200 | C42: Car Accessories | E42: 550 | F42: 1360 | H42: =G42-E42 -> -550 | L42: Products_Images/P06267WaterProof Motor Bike Cover - 100x200.Photo 1.184848.jpg | T42: 46197 | U42: =IF(I42<=0,"Out of Stock","In Stock") -> Out of Stock
A43: P06790 | B43: Xiaomi Waterproof Usb Backpack | C43: Fashion & Accessories | E43: 1500 | F43: 2260 | H43: =G43-E43 -> -1500 | L43: Products_Images/P06790Xiaomi Waterproof Usb Backpack.Photo 1.185006.jpg | T43: 46197 | U43: =IF(I43<=0,"Out of Stock","In Stock") -> Out of Stock
A44: P08048 | B44: Xinchi Tools Adjustable Wrench 10 Inch | C44: Tools & Hardware | E44: 950 | F44: 1560 | H44: =G44-E44 -> -950 | L44: Products_Images/P08048Xinchi Tools Adjustable Wrench 10 Inch.Photo 1.185133.jpg | T44: 46197 | U44: =IF(I44<=0,"Out of Stock","In Stock") -> Out of Stock
A45: P08049 | B45: Xinchi Tools Adjustable Wrench 8 Inch | C45: Tools & Hardware | E45: 650 | F45: 1300 | H45: =G45-E45 -> -650 | L45: Products_Images/P08049Xinchi Tools Adjustable Wrench 8 Inch.Photo 1.185302.jpg | T45: 46197 | U45: =IF(I45<=0,"Out of Stock","In Stock") -> Out of Stock
A46: P03949 | B46: Y1 Wireless Karaoke Speaker | C46: Electronics | E46: 1850 | F46: 2650 | H46: =G46-E46 -> -1850 | L46: Products_Images/P03949Y1 Wireless Karaoke Speaker.Photo 1.185413.jpg | M46: Products_Images/P03949Y1 Wireless Karaoke Speaker.Photo 2.074344.jpg | T46: 46197 | U46: =IF(I46<=0,"Out of Stock","In Stock") -> Out of Stock
A47: P03615 | B47: 10 Pcs Rainbow Nail Cutter Set | C47: Beauty & Personal Care | E47: 550 | F47: 1200 | G47: 990 | H47: =G47-E47 -> 440 | L47: Products_Images/P0361510 Pcs Rainbow Nail Cutter Set.Photo 1.185608.jpg | M47: Products_Images/P0361510 Pcs Rainbow Nail Cutter Set.Photo 2.062341.jpg | T47: 46197 | U47: =IF(I47<=0,"Out of Stock","In Stock") -> Out of Stock
A48: P05933 | B48: 13 inch Tool Empty Box | C48: Tools & Hardware | E48: 1900 | F48: 2850 | G48: 2650 | H48: =G48-E48 -> 750 | L48: Products_Images/P0593313 inch Tool Empty Box.Photo 1.190158.jpg | T48: 46197 | U48: =IF(I48<=0,"Out of Stock","In Stock") -> Out of Stock
A49: P06822 | B49: 16 Pcs Nail Cutter Set | C49: Beauty & Personal Care | E49: 800 | F49: 1600 | H49: =G49-E49 -> -800 | L49: Products_Images/P0682216 Pcs Nail Cutter Set.Photo 1.190317.jpg | T49: 46197 | U49: =IF(I49<=0,"Out of Stock","In Stock") -> Out of Stock
A50: P00810 | B50: 2 in 1 Electric Milk Frother | C50: Kitchen & Dining | E50: 875 | F50: 1650 | H50: =G50-E50 -> -875 | L50: Products_Images/P008102 in 1 Electric Milk Frother.Photo 1.190433.jpg | T50: 46197 | U50: =IF(I50<=0,"Out of Stock","In Stock") -> Out of Stock
A51: P05984 | B51: 5 Led Rechargeable Headlamp | C51: Tools & Hardware | E51: 550 | F51: 1200 | H51: =G51-E51 -> -550 | L51: Products_Images/P059845 Led Rechargeable Headlamp.Photo 1.190641.jpg | T51: 46197 | U51: =IF(I51<=0,"Out of Stock","In Stock") -> Out of Stock
A52: P05895 | B52: 6 Led 2 Pcs Solar Wall Lamp - Up And Down | C52: Home & Living | E52: 850 | F52: 1600 | H52: =G52-E52 -> -850 | L52: Products_Images/P058956 Led 2 Pcs Solar Wall Lamp -_14674997128796848569.Photo 1.190834.jpg | T52: 46197 | U52: =IF(I52<=0,"Out of Stock","In Stock") -> Out of Stock
A53: P04021 | B53: 6 Pcs Screwdriver Set | C53: Tools & Hardware | E53: 875 | F53: 1650 | H53: =G53-E53 -> -875 | L53: Products_Images/P040216 Pcs Screwdriver Set.Photo 1.190953.jpg | T53: 46197 | U53: =IF(I53<=0,"Out of Stock","In Stock") -> Out of Stock
A54: P06350 | B54: 8 In 1 Faucet & Sink Installer | C54: Tools & Hardware | E54: 550 | F54: 1300 | H54: =G54-E54 -> -550 | L54: Products_Images/P063508 In 1 Faucet & Sink Installer.Photo 1.191158.jpg | T54: 46197 | U54: =IF(I54<=0,"Out of Stock","In Stock") -> Out of Stock
A55: P00305 | B55: Allon Key | C55: Tools & Hardware | E55: 310 | F55: 850 | H55: =G55-E55 -> -310 | L55: Products_Images/P00305Allon Key.Photo 1.191322.jpg | T55: 46197 | U55: =IF(I55<=0,"Out of Stock","In Stock") -> Out of Stock
A56: P01982 | B56: Nail Trimmer (Baby) | C56: Beauty & Personal Care | E56: 900 | F56: 1600 | H56: =G56-E56 -> -900 | L56: Products_Images/P01982Nail Trimmer (Baby).Photo 1.191536.jpg | M56: Products_Images/P01982Nail Trimmer (Baby).Photo 2.084400.jpg | N56: Products_Images/P01982Nail Trimmer (Baby).Photo 3.084400.jpg | T56: 46197 | U56: =IF(I56<=0,"Out of Stock","In Stock") -> Out of Stock
A57: P01962 | B57: Felly Canvas Korean Backpack | C57: Fashion & Accessories | E57: 875 | F57: 1690 | G57: 1590 | H57: =G57-E57 -> 715 | L57: Products_Images/P01962Felly Canvas Korean Backpack.Photo 1.191704.jpg | T57: 46197 | U57: =IF(I57<=0,"Out of Stock","In Stock") -> Out of Stock
A58: P00135 | B58: Laser Pointer 303 | C58: Electronics | E58: 1150 | F58: 1650 | G58: 1350 | H58: =G58-E58 -> 200 | L58: Products_Images/P00135Laser Pointer 303.Photo 1.191840.jpg | M58: Products_Images/P00135Laser Pointer 303.Photo 2.093121.jpg | T58: 46197 | U58: =IF(I58<=0,"Out of Stock","In Stock") -> Out of Stock
A59: P02620 | B59: Hanging Luggage Scale | C59: Travel & Accessories | E59: 750 | F59: 1450 | H59: =G59-E59 -> -750 | L59: Products_Images/P02620Hanging Luggage Scale.Photo 1.192126.jpg | T59: 46197 | U59: =IF(I59<=0,"Out of Stock","In Stock") -> Out of Stock
A60: P06351 | B60: Heavy Duty Staple Gun | C60: Tools & Hardware | E60: 925 | F60: 1600 | H60: =G60-E60 -> -925 | L60: Products_Images/P06351Heavy Duty Staple Gun.Photo 1.192328.jpg | T60: 46197 | U60: =IF(I60<=0,"Out of Stock","In Stock") -> Out of Stock
A61: P08432 | B61: High Power Solar Led Street Light - IP66 | C61: Home & Living | E61: 1600 | F61: 2400 | H61: =G61-E61 -> -1600 | L61: Products_Images/P08432High Power Solar Led Street L_5703818820270743096.Photo 1.192442.jpg | T61: 46197 | U61: =IF(I61<=0,"Out of Stock","In Stock") -> Out of Stock
A62: P06898 | B62: Kids Eva Rain Coat | C62: Kids & Baby | E62: 450 | F62: 1000 | H62: =G62-E62 -> -450 | L62: Products_Images/P06898Kids Eva Rain Coat.Photo 1.192616.jpg | T62: 46197 | U62: =IF(I62<=0,"Out of Stock","In Stock") -> Out of Stock
A63: P00464 | B63: Led Mirror Clock | C63: Home & Living | E63: 1550 | F63: 2360 | G63: 1990 | H63: =G63-E63 -> 440 | L63: Products_Images/P00464Led Mirror Clock.Photo 1.192727.jpg | T63: 46197 | U63: =IF(I63<=0,"Out of Stock","In Stock") -> Out of Stock
A64: P08320 | B64: Level Pro 3 Laser Level Tool | C64: Tools & Hardware | E64: 1300 | F64: 1860 | H64: =G64-E64 -> -1300 | L64: Products_Images/P08320Level Pro 3 Laser Level Tool.Photo 1.192941.jpg | T64: 46197 | U64: =IF(I64<=0,"Out of Stock","In Stock") -> Out of Stock
A65: P03875 | B65: Telescopic Duster | C65: Home & Living | E65: 450 | F65: 1000 | H65: =G65-E65 -> -450 | L65: Products_Images/P03875Telescopic Duster.Photo 1.193106.jpg | T65: 46197 | U65: =IF(I65<=0,"Out of Stock","In Stock") -> Out of Stock
A66: P00455 | B66: Luggage Scale | C66: Travel & Accessories | E66: 600 | F66: 1400 | H66: =G66-E66 -> -600 | L66: Products_Images/P00455Luggage Scale.Photo 1.193212.jpg | T66: 46197 | U66: =IF(I66<=0,"Out of Stock","In Stock") -> Out of Stock
A67: P05985 | B67: Luxury Wall Mounted Soap Box | C67: Home & Living | E67: 450 | F67: 1000 | H67: =G67-E67 -> -450 | L67: Products_Images/P05985Luxury Wall Mounted Soap Box.Photo 1.193355.jpg | T67: 46197 | U67: =IF(I67<=0,"Out of Stock","In Stock") -> Out of Stock
A68: P00840 | B68: Massage Gun | C68: Fitness & Health | E68: 1450 | F68: 2000 | H68: =G68-E68 -> -1450 | L68: Products_Images/P00840Massage Gun.Photo 1.193550.jpg | T68: 46197 | U68: =IF(I68<=0,"Out of Stock","In Stock") -> Out of Stock
A69: P00007 | B69: Mini Torch | C69: Tools & Hardware | E69: 400 | F69: 900 | G69: 790 | H69: =G69-E69 -> 390 | L69: Products_Images/P00007Mini Torch.Photo 1.193739.jpg | M69: Products_Images/P00007Mini Torch.Photo 2.112204.jpg | N69: Products_Images/P00007Mini Torch.Photo 3.112204.jpg | O69: Products_Images/P00007Mini Torch.photo 4.112204.jpg | T69: 46197 | U69: =IF(I69<=0,"Out of Stock","In Stock") -> Out of Stock
A70: P00547 | B70: Personal Scale | C70: Fitness & Health | E70: 1450 | F70: 2000 | H70: =G70-E70 -> -1450 | L70: Products_Images/P00547Personal Scale.Photo 1.193849.jpg | T70: 46197 | U70: =IF(I70<=0,"Out of Stock","In Stock") -> Out of Stock
A71: P00111 | B71: Portable Mini Flashlight Q5+COB Led Head Lamp | C71: Tools & Hardware | E71: 400 | F71: 1000 | G71: 790 | H71: =G71-E71 -> 390 | L71: Products_Images/P00111Portable Mini Flashlight Q5+C_15740732991932279554.Photo 1.194008.jpg | T71: 46197 | U71: =IF(I71<=0,"Out of Stock","In Stock") -> Out of Stock
A72: P08034 | B72: Portable Solar Work Light | C72: Home & Living | E72: 1600 | F72: 2500 | H72: =G72-E72 -> -1600 | L72: Products_Images/P08034Portable Solar Work Light.Photo 1.194220.jpg | T72: 46197 | U72: =IF(I72<=0,"Out of Stock","In Stock") -> Out of Stock
A73: P04336 | B73: Round Shape Water Mat | C73: Kids & Baby | E73: 600 | F73: 1200 | H73: =G73-E73 -> -600 | L73: Products_Images/P04336Round Shape Water Mat.Photo 1.194350.jpg | T73: 46197 | U73: =IF(I73<=0,"Out of Stock","In Stock") -> Out of Stock
A74: P00473 | B74: SF 400 Kitchen Scale | C74: Kitchen & Dining | E74: 600 | F74: 1300 | G74: 1100 | H74: =G74-E74 -> 500 | L74: Products_Images/P00473SF 400 Kitchen Scale.Photo 1.194502.jpg | T74: 46197 | U74: =IF(I74<=0,"Out of Stock","In Stock") -> Out of Stock
A75: P07098 | B75: Simulation Steering Wheel Toy | C75: Toys & Kids | E75: 900 | F75: 1650 | H75: =G75-E75 -> -900 | L75: Products_Images/P07098Simulation Steering Wheel Toy.Photo 1.194629.jpg | T75: 46197 | U75: =IF(I75<=0,"Out of Stock","In Stock") -> Out of Stock
A76: P06775 | B76: Sneakers Shoe Cleaner Kit | C76: Beauty & Personal Care | E76: 950 | F76: 1690 | H76: =G76-E76 -> -950 | L76: Products_Images/P06775Sneakers Shoe Cleaner Kit.Photo 1.194743.jpg | T76: 46197 | U76: =IF(I76<=0,"Out of Stock","In Stock") -> Out of Stock
A77: P04206 | B77: Moisturizing Silicone Foot Socks | C77: Beauty & Personal Care | E77: 500 | F77: 1200 | H77: =G77-E77 -> -500 | L77: Products_Images/P04206Moisturizing Silicone Foot Socks.Photo 1.194921.jpg | T77: 46197 | U77: =IF(I77<=0,"Out of Stock","In Stock") -> Out of Stock
A78: P00800 | B78: Speedy Chopper | C78: Kitchen & Dining | E78: 550 | F78: 1300 | H78: =G78-E78 -> -550 | L78: Products_Images/P00800Speedy Chopper.Photo 1.195045.jpg | T78: 46197 | U78: =IF(I78<=0,"Out of Stock","In Stock") -> Out of Stock
A79: P02010 | B79: Stainless Steel Temperature Bottle (500ml) | C79: Kitchen & Dining | E79: 650 | F79: 1350 | H79: =G79-E79 -> -650 | L79: Products_Images/P02010Stainless Steel Temperature B_4655424440761767012.Photo 1.195157.jpg | T79: 46197 | U79: =IF(I79<=0,"Out of Stock","In Stock") -> Out of Stock
A80: P06971 | B80: Stents Bike Phone Holder - Handle | C80: Automotive & Accessories | E80: 650 | F80: 1350 | H80: =G80-E80 -> -650 | L80: Products_Images/P06971Stents Bike Phone Holder - Handle.Photo 1.195259.jpg | T80: 46197 | U80: =IF(I80<=0,"Out of Stock","In Stock") -> Out of Stock
A81: P02669 | B81: Super Absorbent Floor Mat | C81: Home & Living | E81: 440 | F81: 1000 | H81: =G81-E81 -> -440 | L81: Products_Images/P02669Super Absorbent Floor Mat.Photo 1.195411.jpg | T81: 46197 | U81: =IF(I81<=0,"Out of Stock","In Stock") -> Out of Stock
A82: P04733 | B82: Super Absorbent Square Floor Mat | C82: Home & Living | E82: 440 | F82: 1000 | H82: =G82-E82 -> -440 | L82: Products_Images/P04733Super Absorbent Square Floor Mat.Photo 1.195526.jpg | T82: 46197 | U82: =IF(I82<=0,"Out of Stock","In Stock") -> Out of Stock
A83: P02785 | B83: Transparent Waterproof Adhesive Glue | C83: Tools & Hardware | E83: 500 | F83: 1200 | H83: =G83-E83 -> -500 | L83: Products_Images/P02785Transparent Waterproof Adhesive Glue.Photo 1.195653.jpg | T83: 46197 | U83: =IF(I83<=0,"Out of Stock","In Stock") -> Out of Stock
A84: P00357 | B84: Water Play Mat | C84: Kids & Baby | E84: 600 | F84: 1350 | H84: =G84-E84 -> -600 | L84: Products_Images/P00357Water Play Mat.Photo 1.195754.jpg | T84: 46197 | U84: =IF(I84<=0,"Out of Stock","In Stock") -> Out of Stock
A85: P08644 | B85: REMAI PD33 10000mAh Power Bank | C85: Electronics | E85: 2200 | F85: 2660 | G85: 2490 | H85: =G85-E85 -> 290 | L85: Products_Images/P08644REMAI PD33 10000mAh Power Bank.Photo 1.195944.jpg | M85: Products_Images/P08644REMAI PD33 10000mAh Power Bank.Photo 2.172240.jpg | N85: Products_Images/P08644REMAI PD33 10000mAh Power Bank.Photo 3.172240.jpg | O85: Products_Images/P08644REMAI PD33 10000mAh Power Bank.photo 4.172240.jpg | T85: 46197 | U85: =IF(I85<=0,"Out of Stock","In Stock") -> Out of Stock
A86: P08639 | B86: 2 Pcs Max Hand Grip Strengthener | C86: Fitness & Health | E86: 525 | F86: 1260 | H86: =G86-E86 -> -525 | L86: Products_Images/P086392 Pcs Max Hand Grip Strengthener.Photo 1.200125.jpg | T86: 46197 | U86: =IF(I86<=0,"Out of Stock","In Stock") -> Out of Stock
A87: P05826 | B87: Yonsa Electric Cooker - 18cm | C87: Kitchen & Dining | E87: 2150 | F87: 3050 | G87: 2590 | H87: =G87-E87 -> 440 | L87: Products_Images/P05826Yonsa Electric Cooker - 18cm.Photo 1.200231.jpg | T87: 46197 | U87: =IF(I87<=0,"Out of Stock","In Stock") -> Out of Stock
A88: P08607 | B88: 2 in 1 Soap Dispenser Box | C88: Home & Living | E88: 650 | F88: 1600 | H88: =G88-E88 -> -650 | L88: Products_Images/P086072 in 1 Soap Dispenser Box.Photo 1.200355.jpg | M88: Products_Images/P086072 in 1 Soap Dispenser Box.Photo 2.073316.jpg | N88: Products_Images/P086072 in 1 Soap Dispenser Box.Photo 3.073316.jpg | Q88: Products_Files_/P086072 in 1 Soap Dispenser Box.Video Link.080238.mp4 | T88: 46197 | U88: =IF(I88<=0,"Out of Stock","In Stock") -> Out of Stock
A89: P08595 | B89: 2 Pcs Screwdriver Set | C89: Tools & Hardware | E89: 450 | F89: 1000 | H89: =G89-E89 -> -450 | L89: Products_Images/P085952 Pcs Screwdriver Set.Photo 1.200516.jpg | M89: Products_Images/P085952 Pcs Screwdriver Set.Photo 2.083254.jpg | N89: Products_Images/P085952 Pcs Screwdriver Set.Photo 3.083254.jpg | O89: Products_Images/P085952 Pcs Screwdriver Set.photo 4.083254.jpg | T89: 46197 | U89: =IF(I89<=0,"Out of Stock","In Stock") -> Out of Stock
A90: P08666 | B90: 2 Way 7 Layer Dustproof Shoe Rack | C90: Home & Living | E90: 3300 | F90: 3900 | H90: =G90-E90 -> -3300 | L90: Products_Images/P086662 Way 7 Layer Dustproof Shoe Rack.Photo 1.200629.jpg | T90: 46197 | U90: =IF(I90<=0,"Out of Stock","In Stock") -> Out of Stock
A91: P04806 | B91: 20W USB-C Power Adapter | C91: Electronics | E91: 990 | F91: 1690 | G91: 1390 | H91: =G91-E91 -> 400 | L91: Products_Images/P0480620W USB-C Power Adapter.Photo 1.200741.jpg | T91: 46197 | U91: =IF(I91<=0,"Out of Stock","In Stock") -> Out of Stock
A92: P08627 | B92: 2 Pcs Fridge Storage Box | C92: Home & Living | E92: 825 | F92: 1600 | H92: =G92-E92 -> -825 | L92: Products_Images/P086272 Pcs Fridge Storage Box.Photo 1.014932.jpg | T92: 46197 | U92: =IF(I92<=0,"Out of Stock","In Stock") -> Out of Stock
A93: P08659 | B93: REMAX 38W FM Transmitter & Car Charger | C93: Automotive & Accessories | E93: 2100 | F93: 2550 | G93: 2290 | H93: =G93-E93 -> 190 | L93: Products_Images/P08659REMAX 38W FM Transmitter & Car Charger.Photo 1.015144.jpg | T93: 46197 | U93: =IF(I93<=0,"Out of Stock","In Stock") -> Out of Stock
A94: P08606 | B94: 4 Pcs Triangular Solar Step Light | C94: Home & Living | E94: 2200 | F94: 2650 | H94: =G94-E94 -> -2200 | L94: Products_Images/P086064 Pcs Triangular Solar Step Light.Photo 1.015251.jpg | T94: 46197 | U94: =IF(I94<=0,"Out of Stock","In Stock") -> Out of Stock
A95: P08625 | B95: Watch Box & Sun Glasses Organizer | C95: Fashion & Accessorie | E95: 2900 | F95: 3650 | H95: =G95-E95 -> -2900 | L95: Products_Images/P08625Watch Box & Sun Glasses Organizer.Photo 1.015425.jpg | T95: 46197 | U95: =IF(I95<=0,"Out of Stock","In Stock") -> Out of Stock
A96: P08761 | B96: 9pcs Pedicure Set | C96: Beauty & Personal Care | E96: 1250 | F96: 1800 | H96: =G96-E96 -> -1250 | L96: Products_Images/P087619pcs Pedicure Set.Photo 1.015537.jpg | M96: Products_Images/P087619pcs Pedicure Set.Photo 2.084621.jpg | N96: Products_Images/P087619pcs Pedicure Set.Photo 3.084621.jpg | O96: Products_Images/P087619pcs Pedicure Set.photo 4.084621.jpg | T96: 46197 | U96: =IF(I96<=0,"Out of Stock","In Stock") -> Out of Stock
A97: P08664 | B97: REMAI A519 Sport Edition Smartwatch | C97: Electronics | E97: 1900 | F97: 2650 | G97: 2390 | H97: =G97-E97 -> 490 | L97: Products_Images/P08664REMAI A519 Sport Edition Smartwatch.Photo 1.015652.jpg | T97: 46197 | U97: =IF(I97<=0,"Out of Stock","In Stock") -> Out of Stock
A98: P08654 | B98: REMAI AX-79 4-in-1 Fast Charging Cable | C98: Electronics | E98: 875 | F98: 1690 | G98: 1190 | H98: =G98-E98 -> 315 | L98: Products_Images/P08654REMAI AX-79 4-in-1 Fast Charging Cable.Photo 1.015810.jpg | T98: 46197 | U98: =IF(I98<=0,"Out of Stock","In Stock") -> Out of Stock
A99: P08645 | B99: REMAI CW51 Universal Clip Bicycle Holder | C99: Automotive & Accessories | E99: 800 | F99: 1650 | H99: =G99-E99 -> -800 | L99: Products_Images/P08645REMAI CW51 Universal Clip Bic_11325309862918467826.Photo 1.015925.jpg | M99: Products_Images/P08645REMAI CW51 Universal Clip Bic_11325309862918467826.Photo 2.082939.jpg | N99: Products_Images/P08645REMAI CW51 Universal Clip Bic_11325309862918467826.Photo 3.082939.jpg | O99: Products_Images/P08645REMAI CW51 Universal Clip Bic_11325309862918467826.photo 4.082939.jpg | T99: 46197 | U99: =IF(I99<=0,"Out of Stock","In Stock") -> Out of Stock
A100: P08655 | B100: REMAI 120W 3 In 1 Quick Charging Cable - RX088 | C100: Electronics | E100: 450 | F100: 1000 | G100: 750 | H100: =G100-E100 -> 300 | L100: Products_Images/P08655REMAI 120W 3 In 1 Quick Charg_7798255506547790366.Photo 1.020030.jpg | T100: 46197 | U100: =IF(I100<=0,"Out of Stock","In Stock") -> Out of Stock
A101: P08658 | B101: REMAX C7 40W Super Fast Car Charger | C101: Automotive & Accessories | E101: 825 | F101: 1650 | G101: 1250 | H101: =G101-E101 -> 425 | L101: Products_Images/P08658REMAX C7 40W Super Fast Car Charger.Photo 1.020212.jpg | M101: Products_Images/P08658REMAX C7 40W Super Fast Car Charger.Photo 2.081223.jpg | N101: Products_Images/P08658REMAX C7 40W Super Fast Car Charger.Photo 3.081223.jpg | O101: Products_Images/P08658REMAX C7 40W Super Fast Car Charger.photo 4.081223.jpg | T101: 46197 | U101: =IF(I101<=0,"Out of Stock","In Stock") -> Out of Stock
...

Sheet Orders
A1: Order ID | B1: Date | C1: Customer | D1: Phone | E1: Address | F1: Product Code | G1: Product Name | H1: Qty | I1: Total | J1: Status

Sheet Customers
A1: Customer Name | B1: Phone | C1: City | D1: Total Orders | E1: Last Order Date

Sheet Search
A1: Enter Product Code | B1: Product Name | C1: Selling Price | D1: Stock | E1: Status | F1: Category
B2: =IFERROR(VLOOKUP(A2,Products!A:U,2,FALSE),"Not Found") -> Not Found | C2: =IFERROR(VLOOKUP(A2,Products!A:U,7,FALSE),"") | D2: =IFERROR(VLOOKUP(A2,Products!A:U,9,FALSE),"") | E2: =IFERROR(VLOOKUP(A2,Products!A:U,19,FALSE),"") | F2: =IFERROR(VLOOKUP(A2,Products!A:U,3,FALSE),"")

Sheet Dashboard
A1: ZYRO.LK DASHBOARD
A3: Total Products | B3: =COUNTA(Products!A:A)-1 -> 212
A4: Total Stock | B4: =SUM(Products!I:I) -> 0
A5: Potential Profit | B5: =SUM(Products!H:H) -> -124409
